{
    "schema_version": 2,
    "corrections": [
        {
            "name": "dimuonEff_Pat",
            "description": "Scale factors for PAT-PAT dimuon efficiency given from ttbar + J/Psi CR dimuon pt distribution",
            "version": 1,
            "inputs": [
                {
                    "name": "pt",
                    "type": "real",
                    "description": "Dimuon pt of the PAT-PAT dimuon candidate"
                },
                {
                    "name": "scale_factors",
                    "type": "string",
                    "description": "Choose nominal scale factor or one of the uncertainties"
                }
            ],
            "output": {
                "name": "weight",
                "type": "real",
                "description": "Output scale factor (nominal) or uncertainty"
            },
            "data": {
                "nodetype": "binning",
                "input": "pt",
                "edges": [
                    3.0,
                    30.0,
                    60.0,
                    "inf"
                ],
                "content": [
                    {
                        "nodetype": "category",
                        "input": "scale_factors",
                        "content": [
                            {
                                "key": "nominal",
                                "value": 0.6492356675941279
                            },
                            {
                                "key": "up",
                                "value": 0.794059668226818
                            },
                            {
                                "key": "down",
                                "value": 0.5094149409075979
                            }
                        ]
                    },
                    {
                        "nodetype": "category",
                        "input": "scale_factors",
                        "content": [
                            {
                                "key": "nominal",
                                "value": 0.6044578662822876
                            },
                            {
                                "key": "up",
                                "value": 0.7209457229752971
                            },
                            {
                                "key": "down",
                                "value": 0.49375506659805724
                            }
                        ]
                    },
                    {
                        "nodetype": "category",
                        "input": "scale_factors",
                        "content": [
                            {
                                "key": "nominal",
                                "value": 0.9128564109608479
                            },
                            {
                                "key": "up",
                                "value": 1.1341359822312147
                            },
                            {
                                "key": "down",
                                "value": 0.7112861263427717
                            }
                        ]
                    }
                ],
                "flow": "error"
            }
        }
    ]
}